{
	"input_folder":"sk-model/jobs/MetadataInferenceRerun2016_OldSDK/",
	"output_folder":"sk-insights/users/francesco/pipeline_data_v_3_0/",
	"output_email":"frferrar@microsoft.com",
	"num_fragments":0.2,
	"queries":
	[
{"attributes": {"time_division": "weeks", "geoIP.city.name": "true", "geoIP.subdivisions": "true"}, "type_of_analysis": "trends", "name": "AEG_ARTISTS_100/morrissey", "filters": {"ngrams": 1, "geoIP.country": ["US"], "freq_limit": 2, "start_date": "01/10/2013", "users_limit": 2}, "query": ["morrissey"]},
{"attributes": {"time_division": "weeks", "geoIP.city.name": "true", "geoIP.subdivisions": "true"}, "type_of_analysis": "trends", "name": "AEG_ARTISTS_100/amos_lee", "filters": {"ngrams": 2, "geoIP.country": ["US"], "freq_limit": 2, "start_date": "01/10/2013", "users_limit": 2}, "query": ["amos_lee"]},
{"attributes": {"time_division": "weeks", "geoIP.city.name": "true", "geoIP.subdivisions": "true"}, "type_of_analysis": "trends", "name": "AEG_ARTISTS_100/steely_dan", "filters": {"ngrams": 2, "geoIP.country": ["US"], "freq_limit": 2, "start_date": "01/10/2013", "users_limit": 2}, "query": ["steely_dan"]},
{"attributes": {"time_division": "weeks", "geoIP.city.name": "true", "geoIP.subdivisions": "true"}, "type_of_analysis": "trends", "name": "AEG_ARTISTS_100/adventure_club", "filters": {"ngrams": 2, "geoIP.country": ["US"], "freq_limit": 2, "start_date": "01/10/2013", "users_limit": 2}, "query": ["adventure_club"]},
{"attributes": {"time_division": "weeks", "geoIP.city.name": "true", "geoIP.subdivisions": "true"}, "type_of_analysis": "trends", "name": "AEG_ARTISTS_100/the_neighbourhood", "filters": {"ngrams": 2, "geoIP.country": ["US"], "freq_limit": 2, "start_date": "01/10/2013", "users_limit": 2}, "query": ["the_neighbourhood"]},
{"attributes": {"time_division": "weeks", "geoIP.city.name": "true", "geoIP.subdivisions": "true"}, "type_of_analysis": "trends", "name": "AEG_ARTISTS_100/volbeat", "filters": {"ngrams": 1, "geoIP.country": ["US"], "freq_limit": 2, "start_date": "01/10/2013", "users_limit": 2}, "query": ["volbeat"]},
{"attributes": {"time_division": "weeks", "geoIP.city.name": "true", "geoIP.subdivisions": "true"}, "type_of_analysis": "trends", "name": "AEG_ARTISTS_100/steel_panther", "filters": {"ngrams": 2, "geoIP.country": ["US"], "freq_limit": 2, "start_date": "01/10/2013", "users_limit": 2}, "query": ["steel_panther"]},
{"attributes": {"time_division": "weeks", "geoIP.city.name": "true", "geoIP.subdivisions": "true"}, "type_of_analysis": "trends", "name": "AEG_ARTISTS_100/feed_me", "filters": {"ngrams": 2, "geoIP.country": ["US"], "freq_limit": 2, "start_date": "01/10/2013", "users_limit": 2}, "query": ["feed_me"]},
{"attributes": {"time_division": "weeks", "geoIP.city.name": "true", "geoIP.subdivisions": "true"}, "type_of_analysis": "trends", "name": "AEG_ARTISTS_100/kanye_west", "filters": {"ngrams": 2, "geoIP.country": ["US"], "freq_limit": 2, "start_date": "01/10/2013", "users_limit": 2}, "query": ["kanye_west"]},
{"attributes": {"time_division": "weeks", "geoIP.city.name": "true", "geoIP.subdivisions": "true"}, "type_of_analysis": "trends", "name": "AEG_ARTISTS_100/lotus", "filters": {"ngrams": 1, "geoIP.country": ["US"], "freq_limit": 2, "start_date": "01/10/2013", "users_limit": 2}, "query": ["lotus"]},
{"attributes": {"time_division": "weeks", "geoIP.city.name": "true", "geoIP.subdivisions": "true"}, "type_of_analysis": "trends", "name": "AEG_ARTISTS_100/hunter_hayes", "filters": {"ngrams": 2, "geoIP.country": ["US"], "freq_limit": 2, "start_date": "01/10/2013", "users_limit": 2}, "query": ["hunter_hayes"]},
{"attributes": {"time_division": "weeks", "geoIP.city.name": "true", "geoIP.subdivisions": "true"}, "type_of_analysis": "trends", "name": "AEG_ARTISTS_100/steve_hackett", "filters": {"ngrams": 2, "geoIP.country": ["US"], "freq_limit": 2, "start_date": "01/10/2013", "users_limit": 2}, "query": ["steve_hackett"]},
{"attributes": {"time_division": "weeks", "geoIP.city.name": "true", "geoIP.subdivisions": "true"}, "type_of_analysis": "trends", "name": "AEG_ARTISTS_100/st._lucia", "filters": {"ngrams": 2, "geoIP.country": ["US"], "freq_limit": 2, "start_date": "01/10/2013", "users_limit": 2}, "query": ["st._lucia"]},
{"attributes": {"time_division": "weeks", "geoIP.city.name": "true", "geoIP.subdivisions": "true"}, "type_of_analysis": "trends", "name": "AEG_ARTISTS_100/needtobreathe", "filters": {"ngrams": 1, "geoIP.country": ["US"], "freq_limit": 2, "start_date": "01/10/2013", "users_limit": 2}, "query": ["needtobreathe"]},
{"attributes": {"time_division": "weeks", "geoIP.city.name": "true", "geoIP.subdivisions": "true"}, "type_of_analysis": "trends", "name": "AEG_ARTISTS_100/austin_mahone", "filters": {"ngrams": 2, "geoIP.country": ["US"], "freq_limit": 2, "start_date": "01/10/2013", "users_limit": 2}, "query": ["austin_mahone"]},
{"attributes": {"time_division": "weeks", "geoIP.city.name": "true", "geoIP.subdivisions": "true"}, "type_of_analysis": "trends", "name": "AEG_ARTISTS_100/ingrid_michaelson", "filters": {"ngrams": 2, "geoIP.country": ["US"], "freq_limit": 2, "start_date": "01/10/2013", "users_limit": 2}, "query": ["ingrid_michaelson"]},
{"attributes": {"time_division": "weeks", "geoIP.city.name": "true", "geoIP.subdivisions": "true"}, "type_of_analysis": "trends", "name": "AEG_ARTISTS_100/ariana_grande_", "filters": {"ngrams": 3, "geoIP.country": ["US"], "freq_limit": 2, "start_date": "01/10/2013", "users_limit": 2}, "query": ["ariana_grande"]},
{"attributes": {"time_division": "weeks", "geoIP.city.name": "true", "geoIP.subdivisions": "true"}, "type_of_analysis": "trends", "name": "AEG_ARTISTS_100/tommy_emmanuel", "filters": {"ngrams": 2, "geoIP.country": ["US"], "freq_limit": 2, "start_date": "01/10/2013", "users_limit": 2}, "query": ["tommy_emmanuel"]},
{"attributes": {"time_division": "weeks", "geoIP.city.name": "true", "geoIP.subdivisions": "true"}, "type_of_analysis": "trends", "name": "AEG_ARTISTS_100/the_lumineers", "filters": {"ngrams": 2, "geoIP.country": ["US"], "freq_limit": 2, "start_date": "01/10/2013", "users_limit": 2}, "query": ["the_lumineers"]},
{"attributes": {"time_division": "weeks", "geoIP.city.name": "true", "geoIP.subdivisions": "true"}, "type_of_analysis": "trends", "name": "AEG_ARTISTS_100/moe.", "filters": {"ngrams": 1, "geoIP.country": ["US"], "freq_limit": 2, "start_date": "01/10/2013", "users_limit": 2}, "query": ["moe."]},
{"attributes": {"time_division": "weeks", "geoIP.city.name": "true", "geoIP.subdivisions": "true"}, "type_of_analysis": "trends", "name": "AEG_ARTISTS_100/bonobo", "filters": {"ngrams": 1, "geoIP.country": ["US"], "freq_limit": 2, "start_date": "01/10/2013", "users_limit": 2}, "query": ["bonobo"]},
{"attributes": {"time_division": "weeks", "geoIP.city.name": "true", "geoIP.subdivisions": "true"}, "type_of_analysis": "trends", "name": "AEG_ARTISTS_100/cher", "filters": {"ngrams": 1, "geoIP.country": ["US"], "freq_limit": 2, "start_date": "01/10/2013", "users_limit": 2}, "query": ["cher"]},
{"attributes": {"time_division": "weeks", "geoIP.city.name": "true", "geoIP.subdivisions": "true"}, "type_of_analysis": "trends", "name": "AEG_ARTISTS_100/big_gigantic", "filters": {"ngrams": 2, "geoIP.country": ["US"], "freq_limit": 2, "start_date": "01/10/2013", "users_limit": 2}, "query": ["big_gigantic"]},
{"attributes": {"time_division": "weeks", "geoIP.city.name": "true", "geoIP.subdivisions": "true"}, "type_of_analysis": "trends", "name": "AEG_ARTISTS_100/art_garfunkel", "filters": {"ngrams": 2, "geoIP.country": ["US"], "freq_limit": 2, "start_date": "01/10/2013", "users_limit": 2}, "query": ["art_garfunkel"]},
{"attributes": {"time_division": "weeks", "geoIP.city.name": "true", "geoIP.subdivisions": "true"}, "type_of_analysis": "trends", "name": "AEG_ARTISTS_100/shpongle", "filters": {"ngrams": 1, "geoIP.country": ["US"], "freq_limit": 2, "start_date": "01/10/2013", "users_limit": 2}, "query": ["shpongle"]},
{"attributes": {"time_division": "weeks", "geoIP.city.name": "true", "geoIP.subdivisions": "true"}, "type_of_analysis": "trends", "name": "AEG_ARTISTS_100/kenny_chesney", "filters": {"ngrams": 2, "geoIP.country": ["US"], "freq_limit": 2, "start_date": "01/10/2013", "users_limit": 2}, "query": ["kenny_chesney"]},
{"attributes": {"time_division": "weeks", "geoIP.city.name": "true", "geoIP.subdivisions": "true"}, "type_of_analysis": "trends", "name": "AEG_ARTISTS_100/jackie_evancho", "filters": {"ngrams": 2, "geoIP.country": ["US"], "freq_limit": 2, "start_date": "01/10/2013", "users_limit": 2}, "query": ["jackie_evancho"]},
{"attributes": {"time_division": "weeks", "geoIP.city.name": "true", "geoIP.subdivisions": "true"}, "type_of_analysis": "trends", "name": "AEG_ARTISTS_100/beats_antique_", "filters": {"ngrams": 3, "geoIP.country": ["US"], "freq_limit": 2, "start_date": "01/10/2013", "users_limit": 2}, "query": ["beats_antique"]},
{"attributes": {"time_division": "weeks", "geoIP.city.name": "true", "geoIP.subdivisions": "true"}, "type_of_analysis": "trends", "name": "AEG_ARTISTS_100/pinback", "filters": {"ngrams": 1, "geoIP.country": ["US"], "freq_limit": 2, "start_date": "01/10/2013", "users_limit": 2}, "query": ["pinback"]},
{"attributes": {"time_division": "weeks", "geoIP.city.name": "true", "geoIP.subdivisions": "true"}, "type_of_analysis": "trends", "name": "AEG_ARTISTS_100/charlie_wilson", "filters": {"ngrams": 2, "geoIP.country": ["US"], "freq_limit": 2, "start_date": "01/10/2013", "users_limit": 2}, "query": ["charlie_wilson"]},
{"attributes": {"time_division": "weeks", "geoIP.city.name": "true", "geoIP.subdivisions": "true"}, "type_of_analysis": "trends", "name": "AEG_ARTISTS_100/pentatonix_", "filters": {"ngrams": 2, "geoIP.country": ["US"], "freq_limit": 2, "start_date": "01/10/2013", "users_limit": 2}, "query": ["pentatonix"]},
{"attributes": {"time_division": "weeks", "geoIP.city.name": "true", "geoIP.subdivisions": "true"}, "type_of_analysis": "trends", "name": "AEG_ARTISTS_100/eric_church", "filters": {"ngrams": 2, "geoIP.country": ["US"], "freq_limit": 2, "start_date": "01/10/2013", "users_limit": 2}, "query": ["eric_church"]},
{"attributes": {"time_division": "weeks", "geoIP.city.name": "true", "geoIP.subdivisions": "true"}, "type_of_analysis": "trends", "name": "AEG_ARTISTS_100/merle_haggard", "filters": {"ngrams": 2, "geoIP.country": ["US"], "freq_limit": 2, "start_date": "01/10/2013", "users_limit": 2}, "query": ["merle_haggard"]},
{"attributes": {"time_division": "weeks", "geoIP.city.name": "true", "geoIP.subdivisions": "true"}, "type_of_analysis": "trends", "name": "AEG_ARTISTS_100/the_mavericks", "filters": {"ngrams": 2, "geoIP.country": ["US"], "freq_limit": 2, "start_date": "01/10/2013", "users_limit": 2}, "query": ["the_mavericks"]},
{"attributes": {"time_division": "weeks", "geoIP.city.name": "true", "geoIP.subdivisions": "true"}, "type_of_analysis": "trends", "name": "AEG_ARTISTS_100/bruno_mars", "filters": {"ngrams": 2, "geoIP.country": ["US"], "freq_limit": 2, "start_date": "01/10/2013", "users_limit": 2}, "query": ["bruno_mars"]},
{"attributes": {"time_division": "weeks", "geoIP.city.name": "true", "geoIP.subdivisions": "true"}, "type_of_analysis": "trends", "name": "AEG_ARTISTS_100/kid_ink", "filters": {"ngrams": 2, "geoIP.country": ["US"], "freq_limit": 2, "start_date": "01/10/2013", "users_limit": 2}, "query": ["kid_ink"]},
{"attributes": {"time_division": "weeks", "geoIP.city.name": "true", "geoIP.subdivisions": "true"}, "type_of_analysis": "trends", "name": "AEG_ARTISTS_100/alicia_keys", "filters": {"ngrams": 2, "geoIP.country": ["US"], "freq_limit": 2, "start_date": "01/10/2013", "users_limit": 2}, "query": ["alicia_keys"]},
{"attributes": {"time_division": "weeks", "geoIP.city.name": "true", "geoIP.subdivisions": "true"}, "type_of_analysis": "trends", "name": "AEG_ARTISTS_100/bob_dylan", "filters": {"ngrams": 2, "geoIP.country": ["US"], "freq_limit": 2, "start_date": "01/10/2013", "users_limit": 2}, "query": ["bob_dylan"]},
{"attributes": {"time_division": "weeks", "geoIP.city.name": "true", "geoIP.subdivisions": "true"}, "type_of_analysis": "trends", "name": "AEG_ARTISTS_100/skrillex", "filters": {"ngrams": 1, "geoIP.country": ["US"], "freq_limit": 2, "start_date": "01/10/2013", "users_limit": 2}, "query": ["skrillex"]},
{"attributes": {"time_division": "weeks", "geoIP.city.name": "true", "geoIP.subdivisions": "true"}, "type_of_analysis": "trends", "name": "AEG_ARTISTS_100/lindsey_stirling", "filters": {"ngrams": 2, "geoIP.country": ["US"], "freq_limit": 2, "start_date": "01/10/2013", "users_limit": 2}, "query": ["lindsey_stirling"]},
{"attributes": {"time_division": "weeks", "geoIP.city.name": "true", "geoIP.subdivisions": "true"}, "type_of_analysis": "trends", "name": "AEG_ARTISTS_100/john_mellencamp", "filters": {"ngrams": 2, "geoIP.country": ["US"], "freq_limit": 2, "start_date": "01/10/2013", "users_limit": 2}, "query": ["john_mellencamp"]},
{"attributes": {"time_division": "weeks", "geoIP.city.name": "true", "geoIP.subdivisions": "true"}, "type_of_analysis": "trends", "name": "AEG_ARTISTS_100/infected_mushroom", "filters": {"ngrams": 2, "geoIP.country": ["US"], "freq_limit": 2, "start_date": "01/10/2013", "users_limit": 2}, "query": ["infected_mushroom"]},
{"attributes": {"time_division": "weeks", "geoIP.city.name": "true", "geoIP.subdivisions": "true"}, "type_of_analysis": "trends", "name": "AEG_ARTISTS_100/hoodie_allen", "filters": {"ngrams": 2, "geoIP.country": ["US"], "freq_limit": 2, "start_date": "01/10/2013", "users_limit": 2}, "query": ["hoodie_allen"]},
{"attributes": {"time_division": "weeks", "geoIP.city.name": "true", "geoIP.subdivisions": "true"}, "type_of_analysis": "trends", "name": "AEG_ARTISTS_100/primus", "filters": {"ngrams": 1, "geoIP.country": ["US"], "freq_limit": 2, "start_date": "01/10/2013", "users_limit": 2}, "query": ["primus"]},
{"attributes": {"time_division": "weeks", "geoIP.city.name": "true", "geoIP.subdivisions": "true"}, "type_of_analysis": "trends", "name": "AEG_ARTISTS_100/juanes", "filters": {"ngrams": 1, "geoIP.country": ["US"], "freq_limit": 2, "start_date": "01/10/2013", "users_limit": 2}, "query": ["juanes"]},
{"attributes": {"time_division": "weeks", "geoIP.city.name": "true", "geoIP.subdivisions": "true"}, "type_of_analysis": "trends", "name": "AEG_ARTISTS_100/scotty_mccreery", "filters": {"ngrams": 2, "geoIP.country": ["US"], "freq_limit": 2, "start_date": "01/10/2013", "users_limit": 2}, "query": ["scotty_mccreery"]},
{"attributes": {"time_division": "weeks", "geoIP.city.name": "true", "geoIP.subdivisions": "true"}, "type_of_analysis": "trends", "name": "AEG_ARTISTS_100/gramatik", "filters": {"ngrams": 1, "geoIP.country": ["US"], "freq_limit": 2, "start_date": "01/10/2013", "users_limit": 2}, "query": ["gramatik"]},
{"attributes": {"time_division": "weeks", "geoIP.city.name": "true", "geoIP.subdivisions": "true"}, "type_of_analysis": "trends", "name": "AEG_ARTISTS_100/citizen_cope", "filters": {"ngrams": 2, "geoIP.country": ["US"], "freq_limit": 2, "start_date": "01/10/2013", "users_limit": 2}, "query": ["citizen_cope"]},
{"attributes": {"time_division": "weeks", "geoIP.city.name": "true", "geoIP.subdivisions": "true"}, "type_of_analysis": "trends", "name": "AEG_ARTISTS_100/yanni", "filters": {"ngrams": 1, "geoIP.country": ["US"], "freq_limit": 2, "start_date": "01/10/2013", "users_limit": 2}, "query": ["yanni"]},
{"attributes": {"time_division": "weeks", "geoIP.city.name": "true", "geoIP.subdivisions": "true"}, "type_of_analysis": "trends", "name": "AEG_ARTISTS_100/milky_chance", "filters": {"ngrams": 2, "geoIP.country": ["US"], "freq_limit": 2, "start_date": "01/10/2013", "users_limit": 2}, "query": ["milky_chance"]},
{"attributes": {"time_division": "weeks", "geoIP.city.name": "true", "geoIP.subdivisions": "true"}, "type_of_analysis": "trends", "name": "AEG_ARTISTS_100/bon_jovi", "filters": {"ngrams": 2, "geoIP.country": ["US"], "freq_limit": 2, "start_date": "01/10/2013", "users_limit": 2}, "query": ["bon_jovi"]},
{"attributes": {"time_division": "weeks", "geoIP.city.name": "true", "geoIP.subdivisions": "true"}, "type_of_analysis": "trends", "name": "AEG_ARTISTS_100/cody_simpson", "filters": {"ngrams": 2, "geoIP.country": ["US"], "freq_limit": 2, "start_date": "01/10/2013", "users_limit": 2}, "query": ["cody_simpson"]},
{"attributes": {"time_division": "weeks", "geoIP.city.name": "true", "geoIP.subdivisions": "true"}, "type_of_analysis": "trends", "name": "AEG_ARTISTS_100/r5_", "filters": {"ngrams": 2, "geoIP.country": ["US"], "freq_limit": 2, "start_date": "01/10/2013", "users_limit": 2}, "query": ["r5"]},
{"attributes": {"time_division": "weeks", "geoIP.city.name": "true", "geoIP.subdivisions": "true"}, "type_of_analysis": "trends", "name": "AEG_ARTISTS_100/flosstradamus", "filters": {"ngrams": 1, "geoIP.country": ["US"], "freq_limit": 2, "start_date": "01/10/2013", "users_limit": 2}, "query": ["flosstradamus"]},
{"attributes": {"time_division": "weeks", "geoIP.city.name": "true", "geoIP.subdivisions": "true"}, "type_of_analysis": "trends", "name": "AEG_ARTISTS_100/gregg_allman", "filters": {"ngrams": 2, "geoIP.country": ["US"], "freq_limit": 2, "start_date": "01/10/2013", "users_limit": 2}, "query": ["gregg_allman"]},
{"attributes": {"time_division": "weeks", "geoIP.city.name": "true", "geoIP.subdivisions": "true"}, "type_of_analysis": "trends", "name": "AEG_ARTISTS_100/jake_owen", "filters": {"ngrams": 2, "geoIP.country": ["US"], "freq_limit": 2, "start_date": "01/10/2013", "users_limit": 2}, "query": ["jake_owen"]},
{"attributes": {"time_division": "weeks", "geoIP.city.name": "true", "geoIP.subdivisions": "true"}, "type_of_analysis": "trends", "name": "AEG_ARTISTS_100/jackson_browne", "filters": {"ngrams": 2, "geoIP.country": ["US"], "freq_limit": 2, "start_date": "01/10/2013", "users_limit": 2}, "query": ["jackson_browne"]},
{"attributes": {"time_division": "weeks", "geoIP.city.name": "true", "geoIP.subdivisions": "true"}, "type_of_analysis": "trends", "name": "AEG_ARTISTS_100/leonard_cohen", "filters": {"ngrams": 2, "geoIP.country": ["US"], "freq_limit": 2, "start_date": "01/10/2013", "users_limit": 2}, "query": ["leonard_cohen"]},
{"attributes": {"time_division": "weeks", "geoIP.city.name": "true", "geoIP.subdivisions": "true"}, "type_of_analysis": "trends", "name": "AEG_ARTISTS_100/darius_rucker", "filters": {"ngrams": 2, "geoIP.country": ["US"], "freq_limit": 2, "start_date": "01/10/2013", "users_limit": 2}, "query": ["darius_rucker"]},
{"attributes": {"time_division": "weeks", "geoIP.city.name": "true", "geoIP.subdivisions": "true"}, "type_of_analysis": "trends", "name": "AEG_ARTISTS_100/excision", "filters": {"ngrams": 1, "geoIP.country": ["US"], "freq_limit": 2, "start_date": "01/10/2013", "users_limit": 2}, "query": ["excision"]},
{"attributes": {"time_division": "weeks", "geoIP.city.name": "true", "geoIP.subdivisions": "true"}, "type_of_analysis": "trends", "name": "AEG_ARTISTS_100/taylor_swift", "filters": {"ngrams": 2, "geoIP.country": ["US"], "freq_limit": 2, "start_date": "01/10/2013", "users_limit": 2}, "query": ["taylor_swift"]},
{"attributes": {"time_division": "weeks", "geoIP.city.name": "true", "geoIP.subdivisions": "true"}, "type_of_analysis": "trends", "name": "AEG_ARTISTS_100/sammy_adams", "filters": {"ngrams": 2, "geoIP.country": ["US"], "freq_limit": 2, "start_date": "01/10/2013", "users_limit": 2}, "query": ["sammy_adams"]},
{"attributes": {"time_division": "weeks", "geoIP.city.name": "true", "geoIP.subdivisions": "true"}, "type_of_analysis": "trends", "name": "AEG_ARTISTS_100/lord_huron", "filters": {"ngrams": 2, "geoIP.country": ["US"], "freq_limit": 2, "start_date": "01/10/2013", "users_limit": 2}, "query": ["lord_huron"]},
{"attributes": {"time_division": "weeks", "geoIP.city.name": "true", "geoIP.subdivisions": "true"}, "type_of_analysis": "trends", "name": "AEG_ARTISTS_100/future", "filters": {"ngrams": 1, "geoIP.country": ["US"], "freq_limit": 2, "start_date": "01/10/2013", "users_limit": 2}, "query": ["future"]},
{"attributes": {"time_division": "weeks", "geoIP.city.name": "true", "geoIP.subdivisions": "true"}, "type_of_analysis": "trends", "name": "AEG_ARTISTS_100/timeflies", "filters": {"ngrams": 1, "geoIP.country": ["US"], "freq_limit": 2, "start_date": "01/10/2013", "users_limit": 2}, "query": ["timeflies"]},
{"attributes": {"time_division": "weeks", "geoIP.city.name": "true", "geoIP.subdivisions": "true"}, "type_of_analysis": "trends", "name": "AEG_ARTISTS_100/jaheim", "filters": {"ngrams": 1, "geoIP.country": ["US"], "freq_limit": 2, "start_date": "01/10/2013", "users_limit": 2}, "query": ["jaheim"]},
{"attributes": {"time_division": "weeks", "geoIP.city.name": "true", "geoIP.subdivisions": "true"}, "type_of_analysis": "trends", "name": "AEG_ARTISTS_100/j_cole", "filters": {"ngrams": 2, "geoIP.country": ["US"], "freq_limit": 2, "start_date": "01/10/2013", "users_limit": 2}, "query": ["j_cole"]},
{"attributes": {"time_division": "weeks", "geoIP.city.name": "true", "geoIP.subdivisions": "true"}, "type_of_analysis": "trends", "name": "AEG_ARTISTS_100/ed_sheeran", "filters": {"ngrams": 2, "geoIP.country": ["US"], "freq_limit": 2, "start_date": "01/10/2013", "users_limit": 2}, "query": ["ed_sheeran"]},
{"attributes": {"time_division": "weeks", "geoIP.city.name": "true", "geoIP.subdivisions": "true"}, "type_of_analysis": "trends", "name": "AEG_ARTISTS_100/kacey_musgraves", "filters": {"ngrams": 2, "geoIP.country": ["US"], "freq_limit": 2, "start_date": "01/10/2013", "users_limit": 2}, "query": ["kacey_musgraves"]},
{"attributes": {"time_division": "weeks", "geoIP.city.name": "true", "geoIP.subdivisions": "true"}, "type_of_analysis": "trends", "name": "AEG_ARTISTS_100/boston", "filters": {"ngrams": 1, "geoIP.country": ["US"], "freq_limit": 2, "start_date": "01/10/2013", "users_limit": 2}, "query": ["boston"]},
{"attributes": {"time_division": "weeks", "geoIP.city.name": "true", "geoIP.subdivisions": "true"}, "type_of_analysis": "trends", "name": "AEG_ARTISTS_100/say_anything", "filters": {"ngrams": 2, "geoIP.country": ["US"], "freq_limit": 2, "start_date": "01/10/2013", "users_limit": 2}, "query": ["say_anything"]},
{"attributes": {"time_division": "weeks", "geoIP.city.name": "true", "geoIP.subdivisions": "true"}, "type_of_analysis": "trends", "name": "AEG_ARTISTS_100/justin_bieber", "filters": {"ngrams": 2, "geoIP.country": ["US"], "freq_limit": 2, "start_date": "01/10/2013", "users_limit": 2}, "query": ["justin_bieber"]},
{"attributes": {"time_division": "weeks", "geoIP.city.name": "true", "geoIP.subdivisions": "true"}, "type_of_analysis": "trends", "name": "AEG_ARTISTS_100/streetlight_manifesto", "filters": {"ngrams": 2, "geoIP.country": ["US"], "freq_limit": 2, "start_date": "01/10/2013", "users_limit": 2}, "query": ["streetlight_manifesto"]},
{"attributes": {"time_division": "weeks", "geoIP.city.name": "true", "geoIP.subdivisions": "true"}, "type_of_analysis": "trends", "name": "AEG_ARTISTS_100/george_strait", "filters": {"ngrams": 2, "geoIP.country": ["US"], "freq_limit": 2, "start_date": "01/10/2013", "users_limit": 2}, "query": ["george_strait"]},
{"attributes": {"time_division": "weeks", "geoIP.city.name": "true", "geoIP.subdivisions": "true"}, "type_of_analysis": "trends", "name": "AEG_ARTISTS_100/stromae", "filters": {"ngrams": 1, "geoIP.country": ["US"], "freq_limit": 2, "start_date": "01/10/2013", "users_limit": 2}, "query": ["stromae"]},
{"attributes": {"time_division": "weeks", "geoIP.city.name": "true", "geoIP.subdivisions": "true"}, "type_of_analysis": "trends", "name": "AEG_ARTISTS_100/john_fogerty", "filters": {"ngrams": 2, "geoIP.country": ["US"], "freq_limit": 2, "start_date": "01/10/2013", "users_limit": 2}, "query": ["john_fogerty"]},
{"attributes": {"time_division": "weeks", "geoIP.city.name": "true", "geoIP.subdivisions": "true"}, "type_of_analysis": "trends", "name": "AEG_ARTISTS_100/rick_ross", "filters": {"ngrams": 2, "geoIP.country": ["US"], "freq_limit": 2, "start_date": "01/10/2013", "users_limit": 2}, "query": ["rick_ross"]},
{"attributes": {"time_division": "weeks", "geoIP.city.name": "true", "geoIP.subdivisions": "true"}, "type_of_analysis": "trends", "name": "AEG_ARTISTS_100/g-eazy", "filters": {"ngrams": 1, "geoIP.country": ["US"], "freq_limit": 2, "start_date": "01/10/2013", "users_limit": 2}, "query": ["g-eazy"]},
{"attributes": {"time_division": "weeks", "geoIP.city.name": "true", "geoIP.subdivisions": "true"}, "type_of_analysis": "trends", "name": "AEG_ARTISTS_100/pretty_lights", "filters": {"ngrams": 2, "geoIP.country": ["US"], "freq_limit": 2, "start_date": "01/10/2013", "users_limit": 2}, "query": ["pretty_lights"]},
{"attributes": {"time_division": "weeks", "geoIP.city.name": "true", "geoIP.subdivisions": "true"}, "type_of_analysis": "trends", "name": "AEG_ARTISTS_100/willie_nelson", "filters": {"ngrams": 2, "geoIP.country": ["US"], "freq_limit": 2, "start_date": "01/10/2013", "users_limit": 2}, "query": ["willie_nelson"]},
{"attributes": {"time_division": "weeks", "geoIP.city.name": "true", "geoIP.subdivisions": "true"}, "type_of_analysis": "trends", "name": "AEG_ARTISTS_100/lady_antebellum", "filters": {"ngrams": 2, "geoIP.country": ["US"], "freq_limit": 2, "start_date": "01/10/2013", "users_limit": 2}, "query": ["lady_antebellum"]},
{"attributes": {"time_division": "weeks", "geoIP.city.name": "true", "geoIP.subdivisions": "true"}, "type_of_analysis": "trends", "name": "AEG_ARTISTS_100/galactic", "filters": {"ngrams": 1, "geoIP.country": ["US"], "freq_limit": 2, "start_date": "01/10/2013", "users_limit": 2}, "query": ["galactic"]},
{"attributes": {"time_division": "weeks", "geoIP.city.name": "true", "geoIP.subdivisions": "true"}, "type_of_analysis": "trends", "name": "AEG_ARTISTS_100/fifth_harmony", "filters": {"ngrams": 2, "geoIP.country": ["US"], "freq_limit": 2, "start_date": "01/10/2013", "users_limit": 2}, "query": ["fifth_harmony"]},
{"attributes": {"time_division": "weeks", "geoIP.city.name": "true", "geoIP.subdivisions": "true"}, "type_of_analysis": "trends", "name": "AEG_ARTISTS_100/carrie_underwood", "filters": {"ngrams": 2, "geoIP.country": ["US"], "freq_limit": 2, "start_date": "01/10/2013", "users_limit": 2}, "query": ["carrie_underwood"]},
{"attributes": {"time_division": "weeks", "geoIP.city.name": "true", "geoIP.subdivisions": "true"}, "type_of_analysis": "trends", "name": "AEG_ARTISTS_100/schoolboy_q", "filters": {"ngrams": 2, "geoIP.country": ["US"], "freq_limit": 2, "start_date": "01/10/2013", "users_limit": 2}, "query": ["schoolboy_q"]},
{"attributes": {"time_division": "weeks", "geoIP.city.name": "true", "geoIP.subdivisions": "true"}, "type_of_analysis": "trends", "name": "AEG_ARTISTS_100/kendrick_lamar", "filters": {"ngrams": 2, "geoIP.country": ["US"], "freq_limit": 2, "start_date": "01/10/2013", "users_limit": 2}, "query": ["kendrick_lamar"]},
{"attributes": {"time_division": "weeks", "geoIP.city.name": "true", "geoIP.subdivisions": "true"}, "type_of_analysis": "trends", "name": "AEG_ARTISTS_100/the_who", "filters": {"ngrams": 2, "geoIP.country": ["US"], "freq_limit": 2, "start_date": "01/10/2013", "users_limit": 2}, "query": ["the_who"]},
{"attributes": {"time_division": "weeks", "geoIP.city.name": "true", "geoIP.subdivisions": "true"}, "type_of_analysis": "trends", "name": "AEG_ARTISTS_100/tech_n9ne", "filters": {"ngrams": 2, "geoIP.country": ["US"], "freq_limit": 2, "start_date": "01/10/2013", "users_limit": 2}, "query": ["tech_n9ne"]},
{"attributes": {"time_division": "weeks", "geoIP.city.name": "true", "geoIP.subdivisions": "true"}, "type_of_analysis": "trends", "name": "AEG_ARTISTS_100/keith_urban", "filters": {"ngrams": 2, "geoIP.country": ["US"], "freq_limit": 2, "start_date": "01/10/2013", "users_limit": 2}, "query": ["keith_urban"]},
{"attributes": {"time_division": "weeks", "geoIP.city.name": "true", "geoIP.subdivisions": "true"}, "type_of_analysis": "trends", "name": "AEG_ARTISTS_100/katy_perry", "filters": {"ngrams": 2, "geoIP.country": ["US"], "freq_limit": 2, "start_date": "01/10/2013", "users_limit": 2}, "query": ["katy_perry"]},
{"attributes": {"time_division": "weeks", "geoIP.city.name": "true", "geoIP.subdivisions": "true"}, "type_of_analysis": "trends", "name": "AEG_ARTISTS_100/barry_manilow", "filters": {"ngrams": 2, "geoIP.country": ["US"], "freq_limit": 2, "start_date": "01/10/2013", "users_limit": 2}, "query": ["barry_manilow"]},
{"attributes": {"time_division": "weeks", "geoIP.city.name": "true", "geoIP.subdivisions": "true"}, "type_of_analysis": "trends", "name": "AEG_ARTISTS_100/mindless_behavior", "filters": {"ngrams": 2, "geoIP.country": ["US"], "freq_limit": 2, "start_date": "01/10/2013", "users_limit": 2}, "query": ["mindless_behavior"]},
{"attributes": {"time_division": "weeks", "geoIP.city.name": "true", "geoIP.subdivisions": "true"}, "type_of_analysis": "trends", "name": "AEG_ARTISTS_100/suicidal_tendencies", "filters": {"ngrams": 2, "geoIP.country": ["US"], "freq_limit": 2, "start_date": "01/10/2013", "users_limit": 2}, "query": ["suicidal_tendencies"]},
{"attributes": {"time_division": "weeks", "geoIP.city.name": "true", "geoIP.subdivisions": "true"}, "type_of_analysis": "trends", "name": "AEG_ARTISTS_100/paul_mccartney", "filters": {"ngrams": 2, "geoIP.country": ["US"], "freq_limit": 2, "start_date": "01/10/2013", "users_limit": 2}, "query": ["paul_mccartney"]},
{"attributes": {"time_division": "weeks", "geoIP.city.name": "true", "geoIP.subdivisions": "true"}, "type_of_analysis": "trends", "name": "AEG_ARTISTS_100/american_authors", "filters": {"ngrams": 2, "geoIP.country": ["US"], "freq_limit": 2, "start_date": "01/10/2013", "users_limit": 2}, "query": ["american_authors"]}
	]

}